dataflowtool/__init__.py
dataflowtool/dataflowtool/__init__.py
dataflowtool/dataflowtool/cli.py
dataflowtool/dataflowtool/server.py
dataflowtool/frontend/dist/index.html
dataflowtool/frontend/dist/vite.svg
dataflowtool/frontend/dist/assets/index-7dsd_qj4.css
dataflowtool/frontend/dist/assets/index-B2smqEyy.css
dataflowtool/frontend/dist/assets/index-BIPFWNWb.js
dataflowtool/frontend/dist/assets/index-BXEIdKbn.css
dataflowtool/frontend/dist/assets/index-BfaaJgUl.css
dataflowtool/frontend/dist/assets/index-C2bfXBql.css
dataflowtool/frontend/dist/assets/index-CE16PKhe.css
dataflowtool/frontend/dist/assets/index-CLIYy981.js
dataflowtool/frontend/dist/assets/index-CPf0XtuP.js
dataflowtool/frontend/dist/assets/index-CYe4aeO-.css
dataflowtool/frontend/dist/assets/index-Cnv92gpN.css
dataflowtool/frontend/dist/assets/index-CsF2eKn6.js
dataflowtool/frontend/dist/assets/index-CuZHz9As.js
dataflowtool/frontend/dist/assets/index-Cw5_JqJi.css
dataflowtool/frontend/dist/assets/index-DP3OSAom.js
dataflowtool/frontend/dist/assets/index-DaflD5GZ.js
dataflowtool/frontend/dist/assets/index-DjxCWq76.css
dataflowtool/frontend/dist/assets/index-ITrfVf30.js
dataflowtool/frontend/dist/assets/index-L40R70BB.js
dataflowtool/frontend/dist/assets/index-TjhQYi02.js
dataflowtool/frontend/dist/assets/index-b20UmVGn.js
dataflowtool/frontend/dist/assets/index-e0OH7_f4.css
dataflowtool/frontend/dist/assets/index-mCukHYmd.js
dataflowtool-1.0.1.dist-info/LICENSE
dataflowtool-1.0.1.dist-info/METADATA
dataflowtool-1.0.1.dist-info/WHEEL
dataflowtool-1.0.1.dist-info/entry_points.txt
dataflowtool-1.0.1.dist-info/top_level.txt
dataflowtool-1.0.1.dist-info/RECORD
