Metadata-Version: 2.2
Name: dataflowtool
Version: 1.0.1
Summary: A modern data lineage visualization tool with column-level dependency tracking
Home-page: https://github.com/yourusername/dataflowtool
Author: Anirudh
Author-email: isanirudhonline@gmail.com
Keywords: data lineage,dbt,visualization,data dependencies,column lineage
Classifier: Development Status :: 5 - Production/Stable
Classifier: Intended Audience :: Developers
Classifier: Intended Audience :: Information Technology
Classifier: Topic :: Software Development :: Libraries :: Python Modules
Classifier: Topic :: Database :: Database Engines/Servers
Classifier: Topic :: Scientific/Engineering :: Visualization
Classifier: License :: OSI Approved :: MIT License
Classifier: Programming Language :: Python :: 3
Classifier: Programming Language :: Python :: 3.7
Classifier: Programming Language :: Python :: 3.8
Classifier: Programming Language :: Python :: 3.9
Classifier: Programming Language :: Python :: 3.10
Classifier: Programming Language :: Python :: 3.11
Classifier: Framework :: Flask
Classifier: Operating System :: OS Independent
Requires-Python: >=3.7
License-File: LICENSE
Requires-Dist: flask>=2.0.0
Requires-Dist: dbt-core>=1.4.0
Requires-Dist: networkx>=2.6.0
Requires-Dist: pydantic>=1.8.0
Requires-Dist: click>=8.0.0
Dynamic: author
Dynamic: author-email
Dynamic: classifier
Dynamic: description
Dynamic: description-content-type
Dynamic: home-page
Dynamic: keywords
Dynamic: requires-dist
Dynamic: requires-python
Dynamic: summary
